.gitignore
CHANGES.txt
CONTRIBUTORS.txt
README.txt
setup.py
collective/__init__.py
collective.diazo.readheaders.egg-info/PKG-INFO
collective.diazo.readheaders.egg-info/SOURCES.txt
collective.diazo.readheaders.egg-info/dependency_links.txt
collective.diazo.readheaders.egg-info/entry_points.txt
collective.diazo.readheaders.egg-info/namespace_packages.txt
collective.diazo.readheaders.egg-info/not-zip-safe
collective.diazo.readheaders.egg-info/requires.txt
collective.diazo.readheaders.egg-info/top_level.txt
collective/diazo/__init__.py
collective/diazo/readheaders/__init__.py
docs/LICENSE.GPL
docs/LICENSE.txt