Metadata-Version: 1.0
Name: collective.diazo.readheaders
Version: 0.1
Summary: Middleware that allows flexible Diazo theme selection based upon incoming HTTP headers. Extends functionality found in Diazo.
Home-page: https://github.com/collective/collective.diazo.readheaders
Author: David Beitey
Author-email: python@davidjb.com
License: gpl
Keywords: diazo theme wsgi html xslt
Platform: UNKNOWN
Classifier: Programming Language :: Python
